[
  {
    "id": 0,
    "Category": "Bread",
    "Name": "white bread",
    "CO2_100g": 0.065,
    "iconURL": ""
  },
  {
    "id": 1,
    "Category": "Cereal",
    "Name": "Almonds",
    "CO2_100g": 0.218,
    "iconURL": ""
  },
  {
    "id": 2,
    "Category": "Cereal",
    "Name": "Wheat",
    "CO2_100g": 0.051,
    "iconURL": ""
  },
  {
    "id": 3,
    "Category": "Cereal",
    "Name": "Barley",
    "CO2_100g": 0.052,
    "iconURL": ""
  },
  {
    "id": 4,
    "Category": "Cheese",
    "Name": "Cheese slices",
    "CO2_100g": 0.829,
    "iconURL": ""
  },
  {
    "id": 5,
    "Category": "Cheese",
    "Name": "Cheese spread",
    "CO2_100g": 0.62,
    "iconURL": ""
  },
  {
    "id": 6,
    "Category": "Cheese",
    "Name": "Gruyere",
    "CO2_100g": 0.829,
    "iconURL": ""
  },
  {
    "id": 7,
    "Category": "Cheese",
    "Name": "Smoked cheese",
    "CO2_100g": 0.62,
    "iconURL": ""
  },
  {
    "id": 8,
    "Category": "Dessert",
    "Name": "Chocolate",
    "CO2_100g": 1.467,
    "iconURL": ""
  },
  {
    "id": 9,
    "Category": "Meat",
    "Name": "Beef",
    "CO2_100g": 2.776,
    "iconURL": ""
  },
  {
    "id": 10,
    "Category": "Meat",
    "Name": "Chicken",
    "CO2_100g": 0.682,
    "iconURL": ""
  },
  {
    "id": 11,
    "Category": "Meat",
    "Name": "Dried Beef",
    "CO2_100g": 2.776,
    "iconURL": ""
  },
  {
    "id": 12,
    "Category": "Meat",
    "Name": "Ham",
    "CO2_100g": 1.076,
    "iconURL": ""
  },
  {
    "id": 13,
    "Category": "Meat",
    "Name": "Pancetta",
    "CO2_100g": 1.076,
    "iconURL": ""
  },
  {
    "id": 14,
    "Category": "Meat",
    "Name": "Pork",
    "CO2_100g": 1.076,
    "iconURL": ""
  },
  {
    "id": 15,
    "Category": "Meat",
    "Name": "Pork sausages",
    "CO2_100g": 1.076,
    "iconURL": ""
  },
  {
    "id": 16,
    "Category": "Meat",
    "Name": "Sliced beef",
    "CO2_100g": 2.776,
    "iconURL": ""
  },
  {
    "id": 17,
    "Category": "Meat",
    "Name": "Sliced chicken",
    "CO2_100g": 0.68,
    "iconURL": ""
  },
  {
    "id": 18,
    "Category": "Meat",
    "Name": "Tofu",
    "CO2_100g": 0.323,
    "iconURL": ""
  },
  {
    "id": 19,
    "Category": "Meat",
    "Name": "Vegetarian salami",
    "CO2_100g": 0.019,
    "iconURL": ""
  },
  {
    "id": 20,
    "Category": "Meat",
    "Name": "Lamb",
    "CO2_100g": 2.544,
    "iconURL": ""
  },
  {
    "id": 21,
    "Category": "Meat",
    "Name": "Turkey",
    "CO2_100g": 0.59,
    "iconURL": ""
  },
  {
    "id": 22,
    "Category": "Meat",
    "Name": "Rabbit",
    "CO2_100g": 0.361,
    "iconURL": ""
  },
  {
    "id": 23,
    "Category": "Meat",
    "Name": "Cod",
    "CO2_100g": 0.349,
    "iconURL": ""
  },
  {
    "id": 24,
    "Category": "Meat",
    "Name": "Insect",
    "CO2_100g": 0.23,
    "iconURL": ""
  },
  {
    "id": 25,
    "Category": "Milk",
    "Name": "Almond milk",
    "CO2_100g": 0.109,
    "iconURL": ""
  },
  {
    "id": 26,
    "Category": "Milk",
    "Name": "Chocolate milk",
    "CO2_100g": 0.465,
    "iconURL": ""
  },
  {
    "id": 27,
    "Category": "Milk",
    "Name": "Low fat organic milk",
    "CO2_100g": 0.111,
    "iconURL": ""
  },
  {
    "id": 28,
    "Category": "Milk",
    "Name": "Rice milk",
    "CO2_100g": 0.026,
    "iconURL": ""
  },
  {
    "id": 29,
    "Category": "Milk",
    "Name": "UHT milk",
    "CO2_100g": 0.131,
    "iconURL": ""
  },
  {
    "id": 30,
    "Category": "Milk",
    "Name": "Butter",
    "CO2_100g": 1.152,
    "iconURL": ""
  },
  {
    "id": 31,
    "Category": "Milk",
    "Name": "Whole Milk",
    "CO2_100g": 0.14,
    "iconURL": ""
  },
  {
    "id": 32,
    "Category": "Milk",
    "Name": "butter",
    "CO2_100g": 2.374,
    "iconURL": ""
  },
  {
    "id": 33,
    "Category": "Milk",
    "Name": "yoghurt",
    "CO2_100g": 0.122,
    "iconURL": ""
  },
  {
    "id": 34,
    "Category": "Pasta",
    "Name": "Dry Pasta",
    "CO2_100g": 0.149,
    "iconURL": ""
  },
  {
    "id": 35,
    "Category": "Pasta",
    "Name": "Fresh ravioli with meat",
    "CO2_100g": 1.025,
    "iconURL": ""
  },
  {
    "id": 36,
    "Category": "Pasta",
    "Name": "Fresh ravioli with spinach and ricotta",
    "CO2_100g": 0.306,
    "iconURL": ""
  },
  {
    "id": 37,
    "Category": "Pasta",
    "Name": "Risotto rice",
    "CO2_100g": 0.103,
    "iconURL": ""
  },
  {
    "id": 38,
    "Category": "Pasta",
    "Name": "Spaghetti Carbonara pre-made meal",
    "CO2_100g": 0.344,
    "iconURL": ""
  },
  {
    "id": 39,
    "Category": "Pasta",
    "Name": "Wholegrain dry pasta",
    "CO2_100g": 0.149,
    "iconURL": ""
  },
  {
    "id": 40,
    "Category": "Pasta",
    "Name": "noodles",
    "CO2_100g": 0.09,
    "iconURL": ""
  },
  {
    "id": 41,
    "Category": "Vegetable",
    "Name": "Corn",
    "CO2_100g": 0.019,
    "iconURL": ""
  },
  {
    "id": 42,
    "Category": "Vegetable",
    "Name": "Quorn",
    "CO2_100g": 0.019,
    "iconURL": ""
  },
  {
    "id": 43,
    "Category": "Vegetable",
    "Name": "Red kidney beans",
    "CO2_100g": 0.078,
    "iconURL": ""
  },
  {
    "id": 44,
    "Category": "Vegetable",
    "Name": "Peas",
    "CO2_100g": 0.06,
    "iconURL": ""
  },
  {
    "id": 45,
    "Category": "Vegetable",
    "Name": "Chickpeas",
    "CO2_100g": 0.067,
    "iconURL": ""
  },
  {
    "id": 46,
    "Category": "Vegetables",
    "Name": "Lentils",
    "CO2_100g": 0.078,
    "iconURL": ""
  },
  {
    "id": 47,
    "Category": "Vegetables",
    "Name": "Non-free range eggs",
    "CO2_100g": 0.394,
    "iconURL": ""
  },
  {
    "id": 48,
    "Category": "Vegetables",
    "Name": "Eggs",
    "CO2_100g": 0.34,
    "iconURL": ""
  }
]